potato/__init__.py
potato/version.py
potato/apis/__init__.py
potato/apis/inference.py
potato/apis/train.py
potato/apis/test/__init__.py
potato/apis/test/boundary.py
potato/apis/test/edge.py
potato/apis/test/seg.py
potato/core/__init__.py
potato/core/evaluation/__init__.py
potato/core/evaluation/edge_eval_hooks.py
potato/core/evaluation/f_boundary.py
potato/core/evaluation/mmseg_eval_hooks.py
potato/core/evaluation/seg_eval_hooks.py
potato/core/hook/__init__.py
potato/core/hook/potato_wandb_logger.py
potato/datasets/__init__.py
potato/datasets/base_dataset.py
potato/datasets/builder.py
potato/datasets/cityscapes.py
potato/datasets/custom.py
potato/datasets/inria_aerial.py
potato/datasets/isprs.py
potato/datasets/loveda.py
potato/datasets/mmseg_dataset_wrapper.py
potato/datasets/potsdam.py
potato/datasets/pipelines/__init__.py
potato/datasets/pipelines/formatting.py
potato/models/__init__.py
potato/models/builder.py
potato/models/backbones/__init__.py
potato/models/backbones/wider_resnet.py
potato/models/decode_heads/__init__.py
potato/models/decode_heads/binary_hed_head.py
potato/models/decode_heads/debug_gscnn_head.py
potato/models/decode_heads/dense_aspp_head.py
potato/models/decode_heads/gscnn_head.py
potato/models/decode_heads/manyedge_decode_head.py
potato/models/decode_heads/maskgrad_decode_head.py
potato/models/decode_heads/mhjsb_deeplabv3plus.py
potato/models/decode_heads/mhjsb_fcn.py
potato/models/decode_heads/mhjsb_pspnet.py
potato/models/decode_heads/multitask_decode_head.py
potato/models/decode_heads/rpc_head.py
potato/models/decode_heads/sep_aspp_grad_head.py
potato/models/decode_heads/three_stream_head.py
potato/models/decode_heads/ts_jsb.py
potato/models/decode_heads/ts_jsbv1.py
potato/models/decode_heads/ts_jsbv2.py
potato/models/losses/__init__.py
potato/models/losses/accuracy.py
potato/models/losses/boundary_loss.py
potato/models/losses/cross_entropy_loss.py
potato/models/losses/dual_task_loss.py
potato/models/losses/mask_gradient_loss.py
potato_cv-0.1.0.dist-info/LICENSE
potato_cv-0.1.0.dist-info/METADATA
potato_cv-0.1.0.dist-info/WHEEL
potato_cv-0.1.0.dist-info/top_level.txt
potato_cv-0.1.0.dist-info/RECORD
