Metadata-Version: 2.1
Name: potato-cv
Version: 0.1.0
Summary: JSB Framework
Home-page: http://github.com/haruishi43/potato
Author: Haruya Ishikawa
Author-email: 
License: Apache License 2.0
Keywords: computer vision,deep learning
Classifier: Development Status :: 4 - Beta
Classifier: Operating System :: OS Independent
Classifier: Programming Language :: Python :: 3.7
Classifier: Programming Language :: Python :: 3.8
Classifier: Programming Language :: Python :: 3.9
License-File: LICENSE
